<?xml version="1.0" ?>
<annotation>
  <folder>./detection/Images</folder>
  <filename>Tam_d10_407_a_5.jpg</filename>
  <path>./detection/Images/Tam_d10_407_a_5.jpg</path>
  <source>
    <database>Unknown</database>
  </source>
  <size>
    <width>800</width>
    <height>800</height>
    <depth>3</depth>
  </size>
  <segmented>0</segmented>
  <object>
    <name>avocado</name>
    <pose>Unspecified</pose>
    <truncated>0</truncated>
    <difficult>0</difficult>
    <bndbox>
      <xmin>258</xmin>
      <ymin>220</ymin>
      <xmax>536</xmax>
      <ymax>605</ymax>
    </bndbox>
  </object>
</annotation>
